full_adder.v
module full_adder (
    input  A,
    input  B,
    input  Cin,
    output Sum,
    output Cout
);

wire xor_ab;

assign xor_ab = A ^ B;      
assign Sum    = xor_ab ^ Cin;
assign Cout   = (A & B) | (xor_ab & Cin);

endmodule

tb_full_adder.v
`timescale 1ns/1ps

module tb_full_adder;

reg A, B, Cin;
wire Sum, Cout;

full_adder uut (
    .A(A),
    .B(B),
    .Cin(Cin),
    .Sum(Sum),
    .Cout(Cout)
);

initial begin
    $display("A B Cin | Sum Cout");
    $dumpfile("dump.vcd");
    $dumpvars(0, tb_full_adder);
    
    A=0; B=0; Cin=0; #10; $display("%b %b %b | %b   %b", A, B, Cin, Sum, Cout);
    A=0; B=0; Cin=1; #10; $display("%b %b %b | %b   %b", A, B, Cin, Sum, Cout);
    A=0; B=1; Cin=0; #10; $display("%b %b %b | %b   %b", A, B, Cin, Sum, Cout);
    A=0; B=1; Cin=1; #10; $display("%b %b %b | %b   %b", A, B, Cin, Sum, Cout);
    A=1; B=0; Cin=0; #10; $display("%b %b %b | %b   %b", A, B, Cin, Sum, Cout);
    A=1; B=0; Cin=1; #10; $display("%b %b %b | %b   %b", A, B, Cin, Sum, Cout);
    A=1; B=1; Cin=0; #10; $display("%b %b %b | %b   %b", A, B, Cin, Sum, Cout);
    A=1; B=1; Cin=1; #10; $display("%b %b %b | %b   %b", A, B, Cin, Sum, Cout);

    $finish;
end

endmodule

dump.vcd
$date
	Wed Nov 19 10:40:41 2025
$end
$version
	Icarus Verilog
$end
$timescale
	1ps
$end
$scope module tb_full_adder $end
$var wire 1 ! Sum $end
$var wire 1 " Cout $end
$var reg 1 # A $end
$var reg 1 $ B $end
$var reg 1 % Cin $end
$scope module uut $end
$var wire 1 # A $end
$var wire 1 $ B $end
$var wire 1 % Cin $end
$var wire 1 " Cout $end
$var wire 1 ! Sum $end
$var wire 1 & xor_ab $end
$upscope $end
$upscope $end
$enddefinitions $end
$comment Show the parameter values. $end
$dumpall
$end
#0
$dumpvars
0&
0%
0$
0#
0"
0!
$end
#10000
1!
1%
#20000
1&
0%
1$
#30000
1"
0!
1%
#40000
0"
1!
0%
0$
1#
#50000
1"
0!
1%
#60000
0&
0%
1$
#70000
1!
1%
